{
   "type":"FeatureCollection",
   "features":[
      {
         "type":"Feature",
         "geometry":{
            "type":"Point",
            "coordinates":[
               2.387085,
               48.870897
            ]
         },
         "properties":{
            "ville":"Paris",
            "adresse_complete":"Passage Piat 75020 PARIS France",
            "nom_site":"Passage Piat",
            "adresse":"Passage Piat",
            "arrondissement":"20",
            "geo_coordinates":[
               48.870897,
               2.387085
            ],
            "cp":"75020"
         }
      },
      {
         "type":"Feature",
         "geometry":{
            "type":"Point",
            "coordinates":[
            	2.337475,
            	48.886702
            ]
         },
         "properties":{
            "ville":"Paris",
            "adresse_complete":"10 Rue d'Orchampt 75018 PARIS France",
            "nom_site":"Rue d'Orchampt",
            "adresse":"10 Rue d'Orchampt",
            "arrondissement":"18",
            "geo_coordinates":[
               48.886702,
               2.337475
            ],
            "cp":"75018"
         }
      },
      {
         "type":"Feature",
         "geometry":{
            "type":"Point",
            "coordinates":[
               2.327519,
               48.838255
            ]
         },
         "properties":{
            "ville":"PARIS",
            "adresse_complete":"Allée Chauveau Lagarde 75014 PARIS France",
            "nom_site":"Allée Chauveau Lagarde",
            "adresse":"Allée Chauveau Lagarde",
            "arrondissement":"14",
            "geo_coordinates":[
               48.838255,
               2.327519
            ],
            "cp":"75014"
         }
      },
      {
         "type":"Feature",
         "geometry":{
            "type":"Point",
            "coordinates":[
               2.303143,
               48.872478
            ]
         },
         "properties":{
            "ville":"PARIS",
            "adresse_complete":"7 Rue de Berri 75008 PARIS France",
            "nom_site":"Rue de Berri",
            "adresse":"7 Rue de Berri",
            "arrondissement":"08",
            "geo_coordinates":[
               48.872478,
               2.303143
            ],
            "cp":"75008"
         }
      }
   ]
}