{
   "type":"FeatureCollection",
   "features":[
      {
         "type":"Feature",
         "geometry":{
            "type":"Point",
            "coordinates":[
               2.330117,
               48.875336
            ]
         },
         "properties":{
            "ville":"Paris",
            "adresse_complete":"7 Avenue du Coq 75009 PARIS France",
            "nom_site":"Avenue du Coq",
            "adresse":"7 Avenue du Coq",
            "arrondissement":"09",
            "geo_coordinates":[
               48.875336,
               2.330117
            ],
            "cp":"75009"
         }
      },
      {
         "type":"Feature",
         "geometry":{
            "type":"Point",
            "coordinates":[
               2.388825,
               48.892607
            ]
         },
         "properties":{
            "ville":"Paris",
            "adresse_complete":"Galerie de l'Ourcq 75019 PARIS France",
            "nom_site":"Galerie de l'Ourcq",
            "adresse":"Galerie de l'Ourcq",
            "arrondissement":"19",
            "geo_coordinates":[
               48.892607,
               2.388825
            ],
            "cp":"75019"
         }
      },
      {
         "type":"Feature",
         "geometry":{
            "type":"Point",
            "coordinates":[
               2.364958,
               48.837197
            ]
         },
         "properties":{
            "ville":"Paris",
            "adresse_complete":"Rue de l'Infirmerie 75013 PARIS France",
            "nom_site":"Hopital La pitié Salpétrière",
            "adresse":"Rue de l'Infirmerie",
            "arrondissement":"13",
            "geo_coordinates":[
               48.837197,
               2.364958
            ],
            "cp":"75013"
         }
      },
      {
         "type":"Feature",
         "geometry":{
            "type":"Point",
            "coordinates":[
               2.267586,
               48.847369
            ]
         },
         "properties":{
            "ville":"Paris",
            "adresse_complete":"Lycée et Collège Jean Baptiste Say, 11Bis Rue Auteuil, 75016 PARIS France",
            "nom_site":"Lycée et Collège Jean Baptiste Say",
            "adresse":"11Bis Rue Auteuil",
            "arrondissement":"16",
            "geo_coordinates":[
               48.847369,
               2.267586
            ],
            "cp":"75016"
         }
      }
   ]
}